synchronx/__init__.py
synchronx/cli.py
synchronx/main.py
synchronx-0.0.1.dist-info/LICENSE
synchronx-0.0.1.dist-info/WHEEL
synchronx-0.0.1.dist-info/METADATA
synchronx-0.0.1.dist-info/RECORD
